dooGL/__init__.py
dooGL/core/__init__.py
dooGL/core/2d/__init__.py
dooGL/core/2d/arc.py
dooGL/core/2d/bezier_curve.py
dooGL/core/2d/circle.py
dooGL/core/2d/control.py
dooGL/core/2d/ellipse.py
dooGL/core/2d/heart.py
dooGL/core/2d/helper.py
dooGL/core/2d/init.py
dooGL/core/2d/line.py
dooGL/core/2d/main.py
dooGL/core/2d/mouse.py
dooGL/core/2d/polygon.py
dooGL/core/2d/shape.py
dooGL/core/2d/square.py
dooGL/core/2d/star.py
dooGL/core/2d/triangle.py
dooGL/core/_2d/__init__.py
dooGL/core/_2d/arc.py
dooGL/core/_2d/bezier_curve.py
dooGL/core/_2d/circle.py
dooGL/core/_2d/control.py
dooGL/core/_2d/doGl_logo.png
dooGL/core/_2d/ellipse.py
dooGL/core/_2d/heart.py
dooGL/core/_2d/helper.py
dooGL/core/_2d/init.py
dooGL/core/_2d/line.py
dooGL/core/_2d/main.py
dooGL/core/_2d/mouse.py
dooGL/core/_2d/polygon.py
dooGL/core/_2d/shape.py
dooGL/core/_2d/square.py
dooGL/core/_2d/star.py
dooGL/core/_2d/triangle.py
dooGL/core/_3d/__init__.py
dooGL/core/_3d/camera.py
dooGL/core/_3d/cone.py
dooGL/core/_3d/control.py
dooGL/core/_3d/cube.py
dooGL/core/_3d/cylinder.py
dooGL/core/_3d/diamond.py
dooGL/core/_3d/helper.py
dooGL/core/_3d/init.py
dooGL/core/_3d/line.py
dooGL/core/_3d/main.py
dooGL/core/_3d/move.py
dooGL/core/_3d/plane.py
dooGL/core/_3d/prism.py
dooGL/core/_3d/pyramid.py
dooGL/core/_3d/shape.py
dooGL/core/_3d/sphere.py
dooGL/core/_3d/torus.py
dooGL-0.1.9.dist-info/METADATA
dooGL-0.1.9.dist-info/WHEEL
dooGL-0.1.9.dist-info/top_level.txt
dooGL-0.1.9.dist-info/RECORD
